arq/__init__.py
arq/__main__.py
arq/cli.py
arq/connections.py
arq/constants.py
arq/cron.py
arq/jobs.py
arq/logs.py
arq/py.typed
arq/typing.py
arq/utils.py
arq/version.py
arq/worker.py
arq-0.24.0.dist-info/METADATA
arq-0.24.0.dist-info/WHEEL
arq-0.24.0.dist-info/entry_points.txt
arq-0.24.0.dist-info/licenses/LICENSE
arq-0.24.0.dist-info/RECORD
