Metadata-Version: 2.1
Name: arq
Version: 0.24.0
Summary: Job queues in python with asyncio and redis
Project-URL: Homepage, https://github.com/samuelcolvin/arq
Project-URL: Documentation, https://arq-docs.helpmanual.io
Project-URL: Funding, https://github.com/sponsors/samuelcolvin
Project-URL: Source, https://github.com/samuelcolvin/arq
Project-URL: Changelog, https://github.com/samuelcolvin/arq/releases
Author-email: Samuel Colvin <s@muelcolvin.com>
License: The MIT License (MIT)
Classifier: Development Status :: 5 - Production/Stable
Classifier: Environment :: Console
Classifier: Framework :: AsyncIO
Classifier: Intended Audience :: Developers
Classifier: Intended Audience :: Information Technology
Classifier: Intended Audience :: System Administrators
Classifier: License :: OSI Approved :: MIT License
Classifier: Operating System :: POSIX :: Linux
Classifier: Operating System :: Unix
Classifier: Programming Language :: Python
Classifier: Programming Language :: Python :: 3
Classifier: Programming Language :: Python :: 3 :: Only
Classifier: Programming Language :: Python :: 3.7
Classifier: Programming Language :: Python :: 3.8
Classifier: Programming Language :: Python :: 3.9
Classifier: Programming Language :: Python :: 3.10
Classifier: Programming Language :: Python :: 3.11
Classifier: Topic :: Internet
Classifier: Topic :: Software Development :: Libraries :: Python Modules
Classifier: Topic :: System :: Clustering
Classifier: Topic :: System :: Distributed Computing
Classifier: Topic :: System :: Monitoring
Classifier: Topic :: System :: Systems Administration
Requires-Python: >=3.7
Requires-Dist: click>=8.0
Requires-Dist: redis[hiredis]>=4.2.0
Requires-Dist: typing-extensions>=4.1.0
Provides-Extra: watch
Requires-Dist: watchfiles>=0.16; extra == 'watch'
